pikka_bird_server/__init__.py
pikka_bird_server/app.py
pikka_bird_server/database.py
pikka_bird_server/manager.py
pikka_bird_server/web.py
pikka_bird_server/migrations/alembic.ini
pikka_bird_server/migrations/env.py
pikka_bird_server/migrations/README
pikka_bird_server/migrations/script.py.mako
pikka_bird_server/migrations/versions/26f5d92723d_add_collections_collector_version.py
pikka_bird_server/migrations/versions/37440ef063_create_machines.py
pikka_bird_server/migrations/versions/3cc3e86a2e6_create_reports.py
pikka_bird_server/migrations/versions/44c401df80b_constrain_reports.py
pikka_bird_server/migrations/versions/55900322541_add_collections_platform.py
pikka_bird_server/migrations/versions/562ba8022d3_create_collections.py
pikka_bird_server/migrations/versions/d6ebfd0a1b_create_services.py
pikka_bird_server/models/__init__.py
pikka_bird_server/models/base.py
pikka_bird_server/models/collection.py
pikka_bird_server/models/machine.py
pikka_bird_server/models/report.py
pikka_bird_server/models/service.py
pikka_bird_server/routes/__init__.py
pikka_bird_server/routes/collections.py
pikka_bird_server/routes/statics.py
pikka_bird_server-0.1.0.data/scripts/pikka-bird-server
pikka_bird_server-0.1.0.dist-info/DESCRIPTION.rst
pikka_bird_server-0.1.0.dist-info/METADATA
pikka_bird_server-0.1.0.dist-info/metadata.json
pikka_bird_server-0.1.0.dist-info/RECORD
pikka_bird_server-0.1.0.dist-info/top_level.txt
pikka_bird_server-0.1.0.dist-info/WHEEL
