Metadata-Version: 2.0
Name: pikka-bird-server
Version: 0.1.0
Summary: Pikka Bird ops monitoring tool Server component.
Home-page: https://github.com/tiredpixel/pikka-bird-server-py
Author: tiredpixel
Author-email: tp@tiredpixel.com
License: MIT
Keywords: ops monitoring sysadmin
Platform: UNKNOWN
Classifier: Development Status :: 3 - Alpha
Classifier: Intended Audience :: System Administrators
Classifier: License :: OSI Approved :: MIT License
Classifier: Programming Language :: Python :: 2
Classifier: Programming Language :: Python :: 2.7
Classifier: Programming Language :: Python :: 3
Classifier: Programming Language :: Python :: 3.3
Classifier: Programming Language :: Python :: 3.4
Requires-Dist: Flask
Requires-Dist: Flask-Migrate
Requires-Dist: Flask-Script
Requires-Dist: Flask-SQLAlchemy
Requires-Dist: gunicorn
Requires-Dist: msgpack-python
Requires-Dist: psycopg2
